AUTHORS.rst
CONTRIBUTING.rst
HISTORY.rst
LICENSE
MANIFEST.in
README.rst
setup.cfg
setup.py
docs/authors.rst
docs/conf.py
docs/contributing.rst
docs/history.rst
docs/index.rst
docs/installation.rst
docs/readme.rst
docs/usage.rst
ferris/__init__.py
ferris/ferris.py
ferris_build.egg-info/PKG-INFO
ferris_build.egg-info/SOURCES.txt
ferris_build.egg-info/dependency_links.txt
ferris_build.egg-info/not-zip-safe
ferris_build.egg-info/top_level.txt
tests/test_ferris.py