Metadata-Version: 1.1
Name: ferris-build
Version: 0.1.0
Summary: Building tool for Rust
Home-page: https://github.com/yngtodd/ferris
Author: Todd Young
Author-email: youngmt1@ornl.gov
License: BSD license
Keywords: ferris
Platform: UNKNOWN
Classifier: Development Status :: 2 - Pre-Alpha
Classifier: Intended Audience :: Developers
Classifier: License :: OSI Approved :: BSD License
Classifier: Natural Language :: English
Classifier: Programming Language :: Python :: 3.7
